{
	"info": {
		"_postman_id": "cc069e13-a768-4a45-9c21-0683b0a77fde",
		"name": "Acenture",
		"schema": "https://schema.getpostman.com/json/collection/v2.1.0/collection.json",
		"_exporter_id": "43120373"
	},
	"item": [
		{
			"name": "Desafio APi",
			"item": [
				{
					"name": "Criar Usuario",
					"request": {
						"auth": {
							"type": "noauth"
						},
						"method": "POST",
						"header": [],
						"body": {
							"mode": "raw",
							"raw": "{\r\n  \"userName\": \"QaCarlos\",\r\n  \"password\": \"Teste!01\"\r\n}",
							"options": {
								"raw": {
									"language": "json"
								}
							}
						},
						"url": {
							"raw": "https://demoqa.com/Account/v1/User",
							"protocol": "https",
							"host": [
								"demoqa",
								"com"
							],
							"path": [
								"Account",
								"v1",
								"User"
							]
						}
					},
					"response": []
				},
				{
					"name": "Gerar Token De Acesso",
					"request": {
						"auth": {
							"type": "noauth"
						},
						"method": "POST",
						"header": [],
						"body": {
							"mode": "raw",
							"raw": "{\r\n  \"userName\": \"QaCarlos\",\r\n  \"password\": \"Teste!01\"\r\n}",
							"options": {
								"raw": {
									"language": "json"
								}
							}
						},
						"url": {
							"raw": "https://demoqa.com/Account/v1/GenerateToken",
							"protocol": "https",
							"host": [
								"demoqa",
								"com"
							],
							"path": [
								"Account",
								"v1",
								"GenerateToken"
							]
						}
					},
					"response": []
				},
				{
					"name": "Confirmar Autorização",
					"request": {
						"auth": {
							"type": "noauth"
						},
						"method": "POST",
						"header": [],
						"body": {
							"mode": "raw",
							"raw": "{\r\n  \"userName\": \"QaCarlos\",\r\n  \"password\": \"Teste!01\"\r\n}",
							"options": {
								"raw": {
									"language": "json"
								}
							}
						},
						"url": {
							"raw": "https://demoqa.com/Account/v1/Authorized",
							"protocol": "https",
							"host": [
								"demoqa",
								"com"
							],
							"path": [
								"Account",
								"v1",
								"Authorized"
							]
						}
					},
					"response": []
				},
				{
					"name": "Listar Livros ",
					"protocolProfileBehavior": {
						"disableBodyPruning": true
					},
					"request": {
						"auth": {
							"type": "noauth"
						},
						"method": "GET",
						"header": [],
						"body": {
							"mode": "raw",
							"raw": "",
							"options": {
								"raw": {
									"language": "json"
								}
							}
						},
						"url": {
							"raw": "https://demoqa.com/BookStore/v1/Books",
							"protocol": "https",
							"host": [
								"demoqa",
								"com"
							],
							"path": [
								"BookStore",
								"v1",
								"Books"
							]
						}
					},
					"response": []
				},
				{
					"name": "Alugar Dois Livros",
					"request": {
						"auth": {
							"type": "noauth"
						},
						"method": "POST",
						"header": [],
						"body": {
							"mode": "raw",
							"raw": "{\r\n  \"userId\": \"carlos\",\r\n  \"collectionOfIsbns\": [\r\n    {\r\n      \"isbn\": \"9781593277574\"\r\n    },\r\n    {\r\n      \"isbn\": \"9781593275846\"\r\n    }\r\n  ]\r\n}\r\n\r\n\r\n  \r\n\r\n",
							"options": {
								"raw": {
									"language": "json"
								}
							}
						},
						"url": {
							"raw": "https://demoqa.com/BookStore/v1/Books",
							"protocol": "https",
							"host": [
								"demoqa",
								"com"
							],
							"path": [
								"BookStore",
								"v1",
								"Books"
							]
						}
					},
					"response": []
				},
				{
					"name": "Listar Detalhe do Usuario",
					"protocolProfileBehavior": {
						"disableBodyPruning": true
					},
					"request": {
						"auth": {
							"type": "noauth"
						},
						"method": "GET",
						"header": [],
						"body": {
							"mode": "raw",
							"raw": "",
							"options": {
								"raw": {
									"language": "json"
								}
							}
						},
						"url": {
							"raw": "https://demoqa.com/Account/v1/User/{96e60730-a7fd-4d2c-9563-f84745e1632d}",
							"protocol": "https",
							"host": [
								"demoqa",
								"com"
							],
							"path": [
								"Account",
								"v1",
								"User",
								"{96e60730-a7fd-4d2c-9563-f84745e1632d}"
							]
						}
					},
					"response": []
				}
			]
		}
	]
}